demo_24_math_ops/__init__.py
demo_24_math_ops/__version__.py
demo_24_math_ops/addition_module.py
demo_24_math_ops/division_module.py
demo_24_math_ops/multiplication_module.py
demo_24_math_ops/subtraction_module.py
demo24_math_ops-1.0.dist-info/LICENSE
demo24_math_ops-1.0.dist-info/METADATA
demo24_math_ops-1.0.dist-info/WHEEL
demo24_math_ops-1.0.dist-info/top_level.txt
demo24_math_ops-1.0.dist-info/RECORD
