Metadata-Version: 2.2
Name: demo24_math_ops
Version: 1.0
Summary: A demo package for math operations
Author: Raghu
Author-email: raghu@abc.com
Classifier: Programming Language :: Python :: 3
Classifier: License :: OSI Approved :: MIT License
Classifier: Operating System :: OS Independent
Requires-Python: >=3.8
License-File: LICENSE
Dynamic: author
Dynamic: author-email
Dynamic: classifier
Dynamic: requires-python
Dynamic: summary
